kray_zeroconf-0.1.4.data/scripts/zeroconf
utils/__init__.py
utils/parse_configs.py
utils/pre_process_configs.py
utils/stringcalc.py
utils/zc_config.py
kray_zeroconf-0.1.4.dist-info/LICENSE
kray_zeroconf-0.1.4.dist-info/METADATA
kray_zeroconf-0.1.4.dist-info/WHEEL
kray_zeroconf-0.1.4.dist-info/top_level.txt
kray_zeroconf-0.1.4.dist-info/RECORD
